qiniu4blog/__init__.py
qiniu4blog/qiniu4blog.py
qiniu4blog_mk-1.4.2.dist-info/DESCRIPTION.rst
qiniu4blog_mk-1.4.2.dist-info/METADATA
qiniu4blog_mk-1.4.2.dist-info/RECORD
qiniu4blog_mk-1.4.2.dist-info/WHEEL
qiniu4blog_mk-1.4.2.dist-info/entry_points.txt
qiniu4blog_mk-1.4.2.dist-info/metadata.json
qiniu4blog_mk-1.4.2.dist-info/top_level.txt
