Metadata-Version: 2.0
Name: qiniu4blog-mk
Version: 1.4.2
Summary: 写博客用的七牛图床
Home-page: https://github.com/wzyuliyang/qiniu4blog, https://github.com/mirsking/qiniu4blog
Author: wzyuliyang, mirsking
Author-email: wzyuliyang911@gmail.com, mirsking@gmail.com
License: MIT License
Keywords: python qiniu
Platform: UNKNOWN
Requires-Dist: pyperclip
Requires-Dist: qiniu
Requires-Dist: watchdog
